<?xml version="1.0" encoding="UTF-8"?>
<?xml-stylesheet type="text/xsl" href="../xsl/variable.xsl"?>
<variable xmlns:xsi="http://www.w3.org/2001/XMLSchema-instance" xsi:noNamespaceSchemaLocation="../xsd/variable.xsd">
  <name>cl_mvinsethud</name>
  <description>Turns inset HUD for inset POV with multiview on/off.</description>
  <value>
    <boolean>
      <true>Display inset HUD (usually nick of tracked player).</true>
      <false>Do not display inset HUD.</false>
    </boolean>
  </value>
</variable>
